__init__.py
pyevaltool.py
pyevaltool-0.1.8.dist-info/LICENSE
pyevaltool-0.1.8.dist-info/METADATA
pyevaltool-0.1.8.dist-info/WHEEL
pyevaltool-0.1.8.dist-info/top_level.txt
pyevaltool-0.1.8.dist-info/RECORD
