Metadata-Version: 2.1
Name: pyevaltool
Version: 0.1.8
Summary: A package to evaluate the models.
Author-email: Ateendra Jha <ajha@phaf.in>
Project-URL: Homepage, https://www.drateendrajha.com/projects/pyevaltool
Project-URL: Issues, https://www.drateendrajha.com/projects/pyevaltool
Keywords: testing,evaluate,model
Classifier: Programming Language :: Python :: 3
Classifier: License :: OSI Approved :: MIT License
Classifier: Operating System :: OS Independent
Requires-Python: >=3.8
License-File: LICENSE
Requires-Dist: pandas
